MANIFEST.in
README
setup.py
gitinit/__init__.py
gitinit/gitinit.py
gitinit.egg-info/PKG-INFO
gitinit.egg-info/SOURCES.txt
gitinit.egg-info/dependency_links.txt
gitinit.egg-info/entry_points.txt
gitinit.egg-info/top_level.txt
gitinit/gitignores/Actionscript.gitignore
gitinit/gitignores/Android.gitignore
gitinit/gitignores/AppceleratorTitanium.gitignore
gitinit/gitignores/Autotools.gitignore
gitinit/gitignores/Bancha.gitignore
gitinit/gitignores/C++.gitignore
gitinit/gitignores/C.gitignore
gitinit/gitignores/CFWheels.gitignore
gitinit/gitignores/CMake.gitignore
gitinit/gitignores/CakePHP.gitignore
gitinit/gitignores/Clojure.gitignore
gitinit/gitignores/CodeIgniter.gitignore
gitinit/gitignores/Compass.gitignore
gitinit/gitignores/Concrete5.gitignore
gitinit/gitignores/Coq.gitignore
gitinit/gitignores/Dart.gitignore
gitinit/gitignores/Delphi.gitignore
gitinit/gitignores/Django.gitignore
gitinit/gitignores/Drupal.gitignore
gitinit/gitignores/Eagle.gitignore
gitinit/gitignores/Erlang.gitignore
gitinit/gitignores/ExpressionEngine.gitignore
gitinit/gitignores/Finale.gitignore
gitinit/gitignores/ForceDotCom.gitignore
gitinit/gitignores/FuelPHP.gitignore
gitinit/gitignores/GWT.gitignore
gitinit/gitignores/Generic.gitignore
gitinit/gitignores/Go.gitignore
gitinit/gitignores/Grails.gitignore
gitinit/gitignores/Haskell.gitignore
gitinit/gitignores/Java.gitignore
gitinit/gitignores/Jboss.gitignore
gitinit/gitignores/Jekyll.gitignore
gitinit/gitignores/Joomla.gitignore
gitinit/gitignores/Jython.gitignore
gitinit/gitignores/Kohana.gitignore
gitinit/gitignores/LICENSE
gitinit/gitignores/LaTeX.gitignore
gitinit/gitignores/Leiningen.gitignore
gitinit/gitignores/LemonStand.gitignore
gitinit/gitignores/Lilypond.gitignore
gitinit/gitignores/Lithium.gitignore
gitinit/gitignores/Magento.gitignore
gitinit/gitignores/Maven.gitignore
gitinit/gitignores/Node.gitignore
gitinit/gitignores/OCaml.gitignore
gitinit/gitignores/Objective-C.gitignore
gitinit/gitignores/Opa.gitignore
gitinit/gitignores/OracleForms.gitignore
gitinit/gitignores/Perl.gitignore
gitinit/gitignores/PlayFramework.gitignore
gitinit/gitignores/Plone.gitignore
