Metadata-Version: 1.1
Name: gitinit
Version: 1.0.8
Summary: Initiates git with gitignore for provided language
Home-page: https://github.com/iambibhas/gitinit
Author: Bibhas C Debnath
Author-email: me@bibhas.in
License: GPL
Keywords: cli git
Platform: UNKNOWN
Classifier: Development Status :: 4 - Beta
Classifier: Environment :: Console
Classifier: Topic :: Utilities
Classifier: License :: OSI Approved :: GNU General Public License (GPL)
Classifier: Natural Language :: English
Classifier: Programming Language :: Python
